{
  "company_code": "000333",
  "company_name": "美的集团",
  "year": 2020,
  "industry": "制造业",
  "method": "general_rag",
  "indicators": [
    {
      "name": "营业总收入",
      "value": 285709729.0,
      "formula": "直接提取",
      "source_page": 132,
      "source_text": "[段落5] 一、营业总收入 285,709,729",
      "category": "杜邦分析"
    },
    {
      "name": "归属于母公司股东的净利润",
      "value": 27222969.0,
      "formula": "直接提取",
      "source_page": 132,
      "source_text": "[段落1] 归属于母公司股东的净利润 27,222,969",
      "category": "杜邦分析"
    },
    {
      "name": "总资产",
      "value": null,
      "formula": "未在提供段落中找到",
      "source_page": 132,
      "source_text": "提供的文本中未包含资产负债表中的总资产具体数值。",
      "category": "杜邦分析"
    },
    {
      "name": "归属于上市公司股东的净资产（所有者权益）",
      "value": 117516260.0,
      "formula": "直接提取",
      "source_page": 132,
      "source_text": "[段落2] 归属于上市公司股东的净资产（千元） 117,516,260",
      "category": "杜邦分析"
    },
    {
      "name": "加权平均净资产收益率 (ROE)",
      "value": 0.2495,
      "formula": "直接提取",
      "source_page": 132,
      "source_text": "[段落3] 归属于公司普通股股东的净利润 2020年 加权平均净资产收益率(%) 24.95%",
      "category": "杜邦分析"
    },
    {
      "name": "销售净利率",
      "value": 0.0953,
      "formula": "归属于母公司股东的净利润 / 营业总收入",
      "source_page": 132,
      "source_text": "基于[段落1]和[段落5]数值计算：27,222,969 / 285,709,729 ≈ 9.53%",
      "category": "杜邦分析"
    },
    {
      "name": "流动资产",
      "value": 241655325.0,
      "formula": "直接提取",
      "source_page": 130,
      "source_text": "[段落1] 流动资产合计 241,655,325 (2020年12月31日 合并)",
      "category": "Z-Score"
    },
    {
      "name": "流动负债",
      "value": 184150502.0,
      "formula": "直接提取",
      "source_page": 130,
      "source_text": "[段落2] 流动负债合计 184,150,502 (2020年12月31日 合并)",
      "category": "Z-Score"
    },
    {
      "name": "总资产",
      "value": 360382603.0,
      "formula": "直接提取",
      "source_page": 130,
      "source_text": "[段落4] 资产总计 360,382,603 (2020年12月31日 合并)",
      "category": "Z-Score"
    },
    {
      "name": "总负债",
      "value": 236145503.0,
      "formula": "流动负债合计 + 非流动负债合计",
      "source_page": 130,
      "source_text": "[段落2] 流动负债合计 184,150,502；非流动负债合计 51,995,001",
      "category": "Z-Score"
    },
    {
      "name": "营运资本",
      "value": 57504823.0,
      "formula": "流动资产 - 流动负债",
      "source_page": 130,
      "source_text": "[段落1] 流动资产合计 241,655,325；[段落2] 流动负债合计 184,150,502",
      "category": "Z-Score"
    },
    {
      "name": "留存收益",
      "value": null,
      "formula": "盈余公积 + 未分配利润",
      "source_page": 130,
      "source_text": "提供的[段落3]仅包含2019年度的股东权益变动数据，未提供2020年末的合并留存收益具体数值。",
      "category": "Z-Score"
    },
    {
      "name": "息税前利润 (EBIT)",
      "value": null,
      "formula": "净利润 + 利息费用 + 所得税费用",
      "source_page": 130,
      "source_text": "提供的段落中未包含2020年度利润表相关数据。",
      "category": "Z-Score"
    },
    {
      "name": "Altman Z-Score",
      "value": null,
      "formula": "1.2*X1 + 1.4*X2 + 3.3*X3 + 0.6*X4 + 1.0*X5",
      "source_page": 130,
      "source_text": "由于缺少2020年留存收益(X2)、息税前利润(X3)、权益市价(X4)及销售收入(X5)等关键数据，无法计算该指标。",
      "category": "Z-Score"
    },
    {
      "name": "流动资产",
      "value": 241655325.0,
      "formula": "直接提取",
      "source_page": 131,
      "source_text": "流动资产合计 241,655,325",
      "category": "偿债能力"
    },
    {
      "name": "流动负债",
      "value": 184150502.0,
      "formula": "直接提取",
      "source_page": 131,
      "source_text": "流动负债合计 184,150,502",
      "category": "偿债能力"
    },
    {
      "name": "存货",
      "value": 31076529.0,
      "formula": "直接提取",
      "source_page": 131,
      "source_text": "存货 31,076,529",
      "category": "偿债能力"
    },
    {
      "name": "总资产",
      "value": null,
      "formula": "无法计算",
      "source_page": 131,
      "source_text": "提供的段落中未包含资产总计或完整的非流动资产明细",
      "category": "偿债能力"
    },
    {
      "name": "总负债",
      "value": 236145503.0,
      "formula": "流动负债合计 + 非流动负债合计 = 184,150,502 + 51,995,001",
      "source_page": 131,
      "source_text": "流动负债合计 184,150,502；非流动负债合计 51,995,001",
      "category": "偿债能力"
    },
    {
      "name": "营业收入",
      "value": 284221249000.0,
      "formula": "直接提取",
      "source_page": 132,
      "source_text": "其中：营业收入 十七(3) 284,221,249",
      "category": "盈利能力"
    },
    {
      "name": "营业成本",
      "value": 212839592000.0,
      "formula": "直接提取",
      "source_page": 132,
      "source_text": "减：营业成本 四(44) (212,839,592)",
      "category": "盈利能力"
    },
    {
      "name": "净利润",
      "value": 27506542000.0,
      "formula": "直接提取",
      "source_page": 132,
      "source_text": "四、净利润 27,506,542",
      "category": "盈利能力"
    },
    {
      "name": "总资产",
      "value": null,
      "formula": "无",
      "source_page": 132,
      "source_text": "提供的段落中未包含总资产数据",
      "category": "盈利能力"
    },
    {
      "name": "所有者权益（归属于上市公司股东的净资产）",
      "value": 117516260000.0,
      "formula": "直接提取",
      "source_page": 132,
      "source_text": "归属于上市公司股东的净资产（千元） 117,516,260",
      "category": "盈利能力"
    },
    {
      "name": "营业收入",
      "value": 284221249.0,
      "formula": "主营业务收入 + 其他业务收入",
      "source_page": 206,
      "source_text": "2020 年度：主营业务收入 261,474,699，其他业务收入 22,746,550，合计 284,221,249 (单位：人民币千元)",
      "category": "营运能力"
    },
    {
      "name": "营业成本",
      "value": 212839592.0,
      "formula": "主营业务成本 + 其他业务成本",
      "source_page": 206,
      "source_text": "2020 年度：主营业务成本 192,791,358，其他业务成本 20,048,234，合计 212,839,592 (单位：人民币千元)",
      "category": "营运能力"
    },
    {
      "name": "应收账款",
      "value": 22978363.0,
      "formula": "应收账款账面余额 - 坏账准备",
      "source_page": 206,
      "source_text": "2020 年 12 月 31 日：应收账款 23,854,936，减：坏账准备 (876,573)，净额 22,978,363 (单位：人民币千元)",
      "category": "营运能力"
    },
    {
      "name": "存货",
      "value": null,
      "formula": "N/A",
      "source_page": 206,
      "source_text": "提供的检索段落中未包含存货的具体数值。",
      "category": "营运能力"
    },
    {
      "name": "总资产",
      "value": null,
      "formula": "N/A",
      "source_page": 206,
      "source_text": "提供的检索段落中未包含总资产的具体数值。",
      "category": "营运能力"
    },
    {
      "name": "应收账款周转率",
      "value": 13.65,
      "formula": "营业收入 / [(期初应收账款 + 期末应收账款) / 2]",
      "source_page": 206,
      "source_text": "2020年营业收入 284,221,249；2020年末应收账款 22,978,363；2019年末应收账款 18,663,819。",
      "category": "营运能力"
    }
  ],
  "interpretation": "综合以上分析，美的集团（000333）2020年度整体财务状况稳健且优秀，核心基本面表现强劲。\n\n**盈利能力**：公司表现卓越。全年营收超2842亿元，毛利率达25.11%，净利率约9.68%，加权平均ROE高达24.95%。这表明公司具备极强的成本控制与产品溢价能力，高ROE主要由其出色的获利能力驱动，为股东创造了丰厚的回报。\n\n**偿债能力**：短期流动性充裕。流动比率（1.31）与速动比率（1.14）均保持在健康水平（大于1），营运资本超575亿元。这说明公司短期变现能力强，对存货变现的依赖度较低，短期偿债风险极小。\n\n**营运效率**：资金周转高效。应收账款周转率高达13.65次，反映出公司在产业链中具有较强的话语权，资金回笼速度快，债权管理能力优异，有效支撑了业务的高质量增长。\n\n**风险提示**：结合已知总资产（3603.83亿元）与总负债（2361.46亿元）测算，公司资产负债率约为65.5%，虽有充足流动资产覆盖，但仍需关注其整体杠杆水平。此外，由于部分财务明细缺失，无法完成完整的Z-Score破产风险测算及存货周转率评估。建议投资者在认可其核心盈利优势的同时，持续跟踪其长期债务结构及存货去化情况。",
  "metadata": {
    "model": "tengri-2-pro",
    "top_k": 5,
    "rag_queries_count": 5
  }
}