{
  "pdf_path": "/Users/kucha/Projects/毕业论文/年报数据集/医药行业/600085_同仁堂_2023_年度报告.pdf",
  "company_code": "600085",
  "company_name": "同仁堂",
  "industry": "医药行业",
  "year": 2023,
  "indicators": {
    "杜邦分析": {
      "ROE": 0.13342827834917595,
      "销售净利率": 0.1446302518642437,
      "资产周转率": 0.6251233652677732,
      "权益乘数": 1.4757847148864003
    },
    "Z-Score": {
      "Z''-Score": 7.3957402882124805,
      "X1_营运资本/总资产": 0.5383751461106642,
      "X2_留存收益/总资产": 0.3181955742057137,
      "X3_EBIT/总资产": 0.09872279449717516,
      "X4_账面权益/总负债": 2.060251979804647,
      "zone": "安全区"
    },
    "偿债能力": {
      "流动比率": 3.261914769019732,
      "速动比率": 1.9577528675626954,
      "资产负债率": 0.32677047726763847
    },
    "盈利能力": {
      "毛利率": 0.4729226973920713,
      "净利率": 0.1446302518642437,
      "ROA": 0.08585152655729963,
      "ROE": 0.1275219277503809
    },
    "营运能力": {
      "应收账款周转率": 15.157487220229166,
      "存货周转率": 1.1742244701477824,
      "总资产周转率": 0.6251233652677732
    }
  },
  "evidence_map": [
    {
      "category": "杜邦分析",
      "indicator_name": "ROE",
      "indicator_value": 0.13342827834917595,
      "source_text": "北京同仁堂股份有限公司\n2023年年度报告\n对公司将《公开发行证券的公司信息披露解释性公告第1号——非经常性损益》未列举的项目认\n定为的非经常性损益项目且金额重大的，以及将《公开发行证券的公司信息披露解释性公告第1\n号——非经常性损益》中列举的非经常性损益项目界定为经常性损益的项目，应说明原因。\n□适用 √不适用\n其他说明\n□适用 √不适用\n2、 净资产收益率及每股收益\n√适用 □不适用\n加权平均净资产 每股收益\n报告期利润\n收益率（%） 基本每股收益 稀释每股收益\n归属于公司普通股股东的净利润 13.42 1.217\n扣除非经常性损益后归属于公司普通股\n13.32 1.208\n股东的净利润\n3、 境内外会计准则下会计数据差异\n□适用 √不适用\n4、 其他\n□适用 √不适用\n董事长：邸淑兵\n董事会批准报送日期：2024年3月27日\n修订信息\n□适用 √不适用\n221 / 221",
      "page_number": 221,
      "section_title": "2、 净资产收益率及每股收益",
      "relevance_score": 0.6365219950675964
    },
    {
      "category": "杜邦分析",
      "indicator_name": "ROE",
      "indicator_value": 0.13342827834917595,
      "source_text": "加权平均净资产收益率\n13.42 12.72 12.71 增加0.70个百分点 12.01 11.99\n（%）\n扣除非经常性损益后的加\n13.32 12.48 12.47 增加0.84个百分点 11.83 11.81\n权平均净资产收益率（%）\n报告期末公司前三年主要会计数据和财务指标的说明\n□适用 √不适用\n7 / 221",
      "page_number": 7,
      "section_title": "五、 公司股票简况",
      "relevance_score": 0.6687047481536865
    },
    {
      "category": "杜邦分析",
      "indicator_name": "ROE",
      "indicator_value": 0.13342827834917595,
      "source_text": "负债合计 1,557,829,768.59 1,381,882,037.75\n所有者权益（或股东权益）：\n实收资本（或股本） 1,371,470,262.00 1,371,470,262.00\n77 / 221",
      "page_number": 77,
      "section_title": "",
      "relevance_score": 0.5975455641746521
    },
    {
      "category": "Z-Score",
      "indicator_name": "X1_营运资本/总资产",
      "indicator_value": 0.5383751461106642,
      "source_text": "本公司依据信用风险特征将其他应收款划分为若干组合，在组合基础上计算预期信用损失，确定\n组合的依据如下：\n 其他应收款组合1：备用金\n100 / 221",
      "page_number": 100,
      "section_title": "",
      "relevance_score": 0.6110390424728394
    },
    {
      "category": "杜邦分析",
      "indicator_name": "权益乘数",
      "indicator_value": 1.4757847148864003,
      "source_text": "负债合计 1,557,829,768.59 1,381,882,037.75\n所有者权益（或股东权益）：\n实收资本（或股本） 1,371,470,262.00 1,371,470,262.00\n77 / 221",
      "page_number": 77,
      "section_title": "",
      "relevance_score": 0.5992540121078491
    },
    {
      "category": "杜邦分析",
      "indicator_name": "资产周转率",
      "indicator_value": 0.6251233652677732,
      "source_text": "北京同仁堂股份有限公司 2023年年度报告\n(一) 主营业务分析\n1. 利润表及现金流量表相关科目变动分析表\n单位：元 币种：人民币\n科目 本期数 上年同期数 变动比例（%）\n营业收入 17,860,891,456.13 15,372,423,363.17 16.19\n营业成本 9,414,070,490.87 7,870,132,037.30 19.62\n销售费用 3,436,631,969.77 3,071,452,218.52 11.89\n管理费用 1,522,928,135.55 1,342,173,015.28 13.47\n财务费用 -110,139,252.35 -4,630,592.51 -\n研发费用 279,817,301.89 217,446,263.51 28.68\n经营活动产生的现金流量净额 1,869,491,851.11 3,094,296,284.27 -39.58\n投资活动产生的现金流量净额 -76,177,284.46 -211,393,579.65 -\n筹资活动产生的现金流量净额 -1,429,878,161.77 -1,310,229,228.43 ",
      "page_number": 15,
      "section_title": "1. 利润表及现金流量表相关科目变动分析表",
      "relevance_score": 0.5829160213470459
    },
    {
      "category": "Z-Score",
      "indicator_name": "Z''-Score",
      "indicator_value": 7.3957402882124805,
      "source_text": "本公司资本管理政策的目标是为了保障本公司能够持续经营，从而为股东提供回报，并使其他利\n益相关者获益，同时维持最佳的资本结构以降低资本成本。201 / 221",
      "page_number": 201,
      "section_title": "2、资本管理",
      "relevance_score": 0.5914337635040283
    },
    {
      "category": "杜邦分析",
      "indicator_name": "销售净利率",
      "indicator_value": 0.1446302518642437,
      "source_text": "北京同仁堂股份有限公司 2023年年度报告\n加：营业外收入 2,683,881.19 113,886.19\n减：营业外支出 2,865,457.37 1,626,732.59\n三、利润总额（亏损总额以“－”号填\n1,398,453,638.05 1,265,686,469.80\n列）\n减：所得税费用 149,526,294.99 174,791,552.82\n四、净利润（净亏损以“－”号填列） 1,248,927,343.06 1,090,894,916.98\n（一）持续经营净利润（净亏损以\n1,248,927,343.06 1,090,894,916.98\n“－”号填列）\n（二）终止经营净利润（净亏损以\n“－”号填列）\n五、其他综合收益的税后净额\n（一）不能重分类进损益的其他综\n合收益\n1.重新计量设定受益计划变动\n额\n2.权益法下不能转损益的其他\n综合收益\n3.其他权益工具投资公允价值\n变动\n4.企业自身信用风险公允价值\n变动\n（二）将重分类进损益的其他综合\n收益\n1.权益法下可转损益的其他综\n合收益\n2.其他债权投资公允价值变动\n3.金融资产重分类计入其他综\n合收益的金额\n4.其",
      "page_number": 81,
      "section_title": "三、利润总额（亏损总额以“－”号填",
      "relevance_score": 0.6173343062400818
    },
    {
      "category": "Z-Score",
      "indicator_name": "X3_EBIT/总资产",
      "indicator_value": 0.09872279449717516,
      "source_text": "加权平均净资产收益率\n13.42 12.72 12.71 增加0.70个百分点 12.01 11.99\n（%）\n扣除非经常性损益后的加\n13.32 12.48 12.47 增加0.84个百分点 11.83 11.81\n权平均净资产收益率（%）\n报告期末公司前三年主要会计数据和财务指标的说明\n□适用 √不适用\n7 / 221",
      "page_number": 7,
      "section_title": "五、 公司股票简况",
      "relevance_score": 0.6182381510734558
    },
    {
      "category": "Z-Score",
      "indicator_name": "X4_账面权益/总负债",
      "indicator_value": 2.060251979804647,
      "source_text": "负债合计 1,557,829,768.59 1,381,882,037.75\n所有者权益（或股东权益）：\n实收资本（或股本） 1,371,470,262.00 1,371,470,262.00\n77 / 221",
      "page_number": 77,
      "section_title": "",
      "relevance_score": 0.6121156215667725
    },
    {
      "category": "Z-Score",
      "indicator_name": "zone",
      "indicator_value": "安全区",
      "source_text": "3. 财务独立\n36 / 221",
      "page_number": 36,
      "section_title": "（五）信息披露管理",
      "relevance_score": 0.5937046408653259
    },
    {
      "category": "偿债能力",
      "indicator_name": "流动比率",
      "indicator_value": 3.261914769019732,
      "source_text": "北京同仁堂股份有限公司\n2023年年度报告\n（2）流动性风险\n流动性风险，是指本公司在履行以交付现金或其他金融资产结算的义务时遇到资金短缺的风险。管理流动风险时，本公司保持管理层认为充分的现金及现金等价物并对其进行监控，以满足本公\n司经营需要，并降低现金流量波动的影响。本公司管理层对银行借款的使用情况进行监控并确保\n遵守借款协议。同时从主要金融机构获得提供足够备用资金的承诺，以满足短期和长期的资金需\n求。本公司通过经营业务产生的资金及银行及其他借款来筹措营运资金。本公司持有的金融负债按未折现剩余合同现金流量的到期期限分析如下（单位：万元）：\n项 目 期末余额 到期期限 上年年末余额 到期期限\n短期借款 9,302.48 一年以内 30,953.20 一年以内\n应付票据 22,544.72 一年以内 4,386.72 一年以内\n应付账款 427,618.67 -- 344,728.60 --\n其他应付款 57,247.79 -- 51,757.28 --\n一年内到期的非流动负债 52,384.42 一年以内 48,589.03 一年以内\n长期借款 142,975.08 详见第十节、七、4",
      "page_number": 200,
      "section_title": "",
      "relevance_score": 0.6118872761726379
    },
    {
      "category": "偿债能力",
      "indicator_name": "资产负债率",
      "indicator_value": 0.32677047726763847,
      "source_text": "长期应付款 十、七、48 9,505,675.28 9,135,740.00\n长期应付职工薪酬 十、七、49 24,250.52 339,579.73\n预计负债\n递延收益 十、七、51 157,567,528.73 153,956,130.42\n递延所得税负债 十、七、29 7,935,393.06 8,816,914.37\n其他非流动负债\n非流动负债合计 2,670,530,314.02 2,254,816,996.59\n负债合计 9,832,343,990.70 8,590,423,576.47\n所有者权益（或股东权益）：\n实收资本（或股本） 十、七、53 1,371,470,262.00 1,371,470,262.00\n其他权益工具\n75 / 221",
      "page_number": 75,
      "section_title": "",
      "relevance_score": 0.615757942199707
    },
    {
      "category": "偿债能力",
      "indicator_name": "资产负债率",
      "indicator_value": 0.32677047726763847,
      "source_text": "负债合计 1,557,829,768.59 1,381,882,037.75\n所有者权益（或股东权益）：\n实收资本（或股本） 1,371,470,262.00 1,371,470,262.00\n77 / 221",
      "page_number": 77,
      "section_title": "",
      "relevance_score": 0.6286187171936035
    },
    {
      "category": "盈利能力",
      "indicator_name": "净利率",
      "indicator_value": 0.1446302518642437,
      "source_text": "聚力高质量党建引领高质量发展，全年实现营业收入 1,786,089.15 万元，同比增长 16.19%，归属于上市\n公司股东的净利润166,883.45万元，同比增长16.92%。14 / 221",
      "page_number": 14,
      "section_title": "四、报告期内核心竞争力分析",
      "relevance_score": 0.6246552467346191
    },
    {
      "category": "盈利能力",
      "indicator_name": "毛利率",
      "indicator_value": 0.4729226973920713,
      "source_text": "北京同仁堂股份有限公司 2023年年度报告\n(1). 主营业务分行业、分产品、分地区、分销售模式情况\n单位:万元 币种:人民币\n主营业务分行业情况\n营业收入比\n毛利率 营业成本比上年 毛利率比上年增减\n分行业 营业收入 营业成本 上年增减\n（%） 增减（%） （%）\n（%）\n医药工业\n1,107,943.55 587,594.57 46.97 12.60 16.96 减少1.98个百分点\n主营收入\n医药商业\n1,024,641.53 705,837.07 31.11 20.82 20.53 增加0.16个百分点\n主营收入\n主营业务分产品情况\n营业收入比\n毛利率 营业成本比上年 毛利率比上年增减\n分产品 营业收入 营业成本 上年增减\n（%） 增减（%） （%）\n（%）\n前五名系\n495,256.28 223,754.18 54.82 9.97 25.01 减少5.44个百分点\n列\n主营业务分地区情况\n营业收入比\n毛利率 营业成本比上年 毛利率比上年增减\n分地区 营业收入 营业成本 上年增减\n（%） 增减（%） （%）\n（%）\n中国境内 1,649,272.09 904,949.66 45",
      "page_number": 16,
      "section_title": "",
      "relevance_score": 0.6224985718727112
    },
    {
      "category": "盈利能力",
      "indicator_name": "毛利率",
      "indicator_value": 0.4729226973920713,
      "source_text": "北京同仁堂股份有限公司 2023年年度报告\n(一) 主营业务分析\n1. 利润表及现金流量表相关科目变动分析表\n单位：元 币种：人民币\n科目 本期数 上年同期数 变动比例（%）\n营业收入 17,860,891,456.13 15,372,423,363.17 16.19\n营业成本 9,414,070,490.87 7,870,132,037.30 19.62\n销售费用 3,436,631,969.77 3,071,452,218.52 11.89\n管理费用 1,522,928,135.55 1,342,173,015.28 13.47\n财务费用 -110,139,252.35 -4,630,592.51 -\n研发费用 279,817,301.89 217,446,263.51 28.68\n经营活动产生的现金流量净额 1,869,491,851.11 3,094,296,284.27 -39.58\n投资活动产生的现金流量净额 -76,177,284.46 -211,393,579.65 -\n筹资活动产生的现金流量净额 -1,429,878,161.77 -1,310,229,228.43 ",
      "page_number": 15,
      "section_title": "1. 利润表及现金流量表相关科目变动分析表",
      "relevance_score": 0.6214441061019897
    },
    {
      "category": "偿债能力",
      "indicator_name": "速动比率",
      "indicator_value": 1.9577528675626954,
      "source_text": "北京同仁堂股份有限公司 2023年年度报告\n其中：应收利息\n应收股利\n买入返售金融资产\n存货 6,694,368,428.37 6,694,368,428.37\n合同资产\n持有待售资产\n一年内到期的非流动资产 917,431.19 917,431.19\n其他流动资产 102,024,434.98 102,024,434.98\n流动资产合计 20,559,416,226.02 20,559,416,226.02\n非流动资产：\n发放贷款和垫款\n债权投资\n其他债权投资\n长期应收款 1,128,207.14 1,128,207.14\n长期股权投资 19,449,670.53 19,449,670.53\n其他权益工具投资 8,591,358.31 8,591,358.31\n其他非流动金融资产 90,000.00 90,000.00\n投资性房地产\n固定资产 3,808,597,332.93 3,808,597,332.93\n在建工程 136,023,490.68 136,023,490.68\n生产性生物资产 4,115,075.81 4,115,075.81\n油气资产\n使用权资产 1,344,33",
      "page_number": 124,
      "section_title": "",
      "relevance_score": 0.5698922276496887
    },
    {
      "category": "偿债能力",
      "indicator_name": "速动比率",
      "indicator_value": 1.9577528675626954,
      "source_text": "北京同仁堂股份有限公司 2023年年度报告\n二、 财务报表\n合并资产负债表\n2023年12月31日\n编制单位: 北京同仁堂股份有限公司\n单位:元 币种:人民币\n项目 附注 2023年12月31日 2022年12月31日\n流动资产：\n货币资金 十、七、1 12,131,896,561.98 11,623,986,433.44\n结算备付金\n拆出资金\n交易性金融资产 十、七、2 370,376.67 428,584.04\n衍生金融资产\n应收票据 十、七、4 238,833,849.91 464,210,229.92\n应收账款 十、七、5 1,055,560,325.33 1,301,148,434.72\n应收款项融资 十、七、7 79,484,406.66 115,827,605.64\n预付款项 十、七、8 138,782,723.97 160,632,481.81\n应收保费\n应收分保账款\n应收分保合同准备金\n其他应收款 十、七、9 112,396,032.46 95,872,161.91\n其中：应收利息\n应收股利\n买入返售金融资产\n存货 十、七、10 9,340,164,542.46 6,",
      "page_number": 74,
      "section_title": "二、 财务报表",
      "relevance_score": 0.5812672972679138
    },
    {
      "category": "盈利能力",
      "indicator_name": "ROA",
      "indicator_value": 0.08585152655729963,
      "source_text": "加权平均净资产收益率\n13.42 12.72 12.71 增加0.70个百分点 12.01 11.99\n（%）\n扣除非经常性损益后的加\n13.32 12.48 12.47 增加0.84个百分点 11.83 11.81\n权平均净资产收益率（%）\n报告期末公司前三年主要会计数据和财务指标的说明\n□适用 √不适用\n7 / 221",
      "page_number": 7,
      "section_title": "五、 公司股票简况",
      "relevance_score": 0.6140891313552856
    },
    {
      "category": "Z-Score",
      "indicator_name": "X2_留存收益/总资产",
      "indicator_value": 0.3181955742057137,
      "source_text": "加权平均净资产收益率\n13.42 12.72 12.71 增加0.70个百分点 12.01 11.99\n（%）\n扣除非经常性损益后的加\n13.32 12.48 12.47 增加0.84个百分点 11.83 11.81\n权平均净资产收益率（%）\n报告期末公司前三年主要会计数据和财务指标的说明\n□适用 √不适用\n7 / 221",
      "page_number": 7,
      "section_title": "五、 公司股票简况",
      "relevance_score": 0.6107048392295837
    },
    {
      "category": "盈利能力",
      "indicator_name": "ROE",
      "indicator_value": 0.1275219277503809,
      "source_text": "北京同仁堂股份有限公司\n2023年年度报告\n对公司将《公开发行证券的公司信息披露解释性公告第1号——非经常性损益》未列举的项目认\n定为的非经常性损益项目且金额重大的，以及将《公开发行证券的公司信息披露解释性公告第1\n号——非经常性损益》中列举的非经常性损益项目界定为经常性损益的项目，应说明原因。\n□适用 √不适用\n其他说明\n□适用 √不适用\n2、 净资产收益率及每股收益\n√适用 □不适用\n加权平均净资产 每股收益\n报告期利润\n收益率（%） 基本每股收益 稀释每股收益\n归属于公司普通股股东的净利润 13.42 1.217\n扣除非经常性损益后归属于公司普通股\n13.32 1.208\n股东的净利润\n3、 境内外会计准则下会计数据差异\n□适用 √不适用\n4、 其他\n□适用 √不适用\n董事长：邸淑兵\n董事会批准报送日期：2024年3月27日\n修订信息\n□适用 √不适用\n221 / 221",
      "page_number": 221,
      "section_title": "2、 净资产收益率及每股收益",
      "relevance_score": 0.6365219950675964
    },
    {
      "category": "盈利能力",
      "indicator_name": "ROE",
      "indicator_value": 0.1275219277503809,
      "source_text": "加权平均净资产收益率\n13.42 12.72 12.71 增加0.70个百分点 12.01 11.99\n（%）\n扣除非经常性损益后的加\n13.32 12.48 12.47 增加0.84个百分点 11.83 11.81\n权平均净资产收益率（%）\n报告期末公司前三年主要会计数据和财务指标的说明\n□适用 √不适用\n7 / 221",
      "page_number": 7,
      "section_title": "五、 公司股票简况",
      "relevance_score": 0.6687047481536865
    },
    {
      "category": "盈利能力",
      "indicator_name": "ROE",
      "indicator_value": 0.1275219277503809,
      "source_text": "负债合计 1,557,829,768.59 1,381,882,037.75\n所有者权益（或股东权益）：\n实收资本（或股本） 1,371,470,262.00 1,371,470,262.00\n77 / 221",
      "page_number": 77,
      "section_title": "",
      "relevance_score": 0.5975455641746521
    },
    {
      "category": "营运能力",
      "indicator_name": "总资产周转率",
      "indicator_value": 0.6251233652677732,
      "source_text": "加权平均净资产收益率\n13.42 12.72 12.71 增加0.70个百分点 12.01 11.99\n（%）\n扣除非经常性损益后的加\n13.32 12.48 12.47 增加0.84个百分点 11.83 11.81\n权平均净资产收益率（%）\n报告期末公司前三年主要会计数据和财务指标的说明\n□适用 √不适用\n7 / 221",
      "page_number": 7,
      "section_title": "五、 公司股票简况",
      "relevance_score": 0.590175211429596
    },
    {
      "category": "营运能力",
      "indicator_name": "应收账款周转率",
      "indicator_value": 15.157487220229166,
      "source_text": "北京同仁堂股份有限公司\n2023年年度报告\n十九、 母公司财务报表主要项目注释\n1、 应收账款\n(1). 按账龄披露\n√适用 □不适用\n单位：元币种：人民币\n账龄 期末账面余额 期初账面余额\n1年以内\n其中：1年以内分项\n1年以内 19,272,665.70 34,927,464.89\n1年以内小计 19,272,665.70 34,927,464.89\n1至2年\n2至3年 36,280.69\n3年以上\n3至4年\n4至5年 22,581,961.33\n5年以上 69,410,736.39 70,820,319.43\n合计 88,683,402.09 128,366,026.34\n(2). 按坏账计提方法分类披露\n√适用 □不适用\n单位：元币种：人民币\n期末余额 期初余额\n账面\n账面余额 坏账准备 账面余额 坏账准备\n价值\n类别 账面\n计提 计提\n比例 价值 比例\n金额 金额 比例 金额 金额 比例\n(%) (%)\n(%) (%)\n按单项计提坏 46.9\n41,649,292.55 41,649,292.55 100.00 44,007,986.25 34.28 44,007,986.2",
      "page_number": 212,
      "section_title": "十九、 母公司财务报表主要项目注释",
      "relevance_score": 0.5907964110374451
    },
    {
      "category": "营运能力",
      "indicator_name": "存货周转率",
      "indicator_value": 1.1742244701477824,
      "source_text": "（3）评价存货滞销迹象相关的分析指标如周转率、库龄等，并对比销售预算和生产计划；71 / 221",
      "page_number": 71,
      "section_title": "第十节 财务报告",
      "relevance_score": 0.6260609030723572
    }
  ],
  "interpretation": "**同仁堂（600085）2023年度财务分析报告**\n\n**一、企业概况与分析期间**\n本报告分析主体为同仁堂（股票代码：600085），所属行业为医药行业，分析期间为2023年度。2023年，公司全年实现营业收入178.61亿元，同比增长16.19%；营业成本94.14亿元，同比增长19.62% [第15页]；实现净利润25.83亿元 [数据来源: 已验证的合并报表原始数据]。整体来看，公司在报告期内保持了稳健的经营规模扩张。\n\n**二、盈利能力分析**\n基于杜邦分析体系，公司2023年度的净资产收益率（ROE）为0.1334，年报披露的加权平均净资产收益率为13.42%，较上年增加0.70个百分点 [第7页]。其ROE的驱动因素具体分析如下：\n1. **销售净利率**：公司销售净利率为0.1446，综合毛利率为0.4729，处于较高水平。需要注意的是，公司核心的医药工业板块毛利率为46.97%，比上年减少1.98个百分点 [第16页]，这与营业成本（19.62%）增速高于营业收入（16.19%）增速的特征相符 [第15页]。\n2. **资产周转率**：总资产周转率为0.6251，表明公司每1元资产能产生约0.625元的营业收入，资产创收效率处于稳健水平。\n3. **权益乘数**：权益乘数为1.4758，表明公司利用了适度的财务杠杆来放大股东回报，整体资本结构较为保守。\n综合来看，公司的总资产净利率（ROA）为0.0859，其较强的盈利能力主要依赖于产品较高的利润空间（高净利率）而非高杠杆驱动。\n\n**三、偿债能力分析**\n1. **短期偿债能力**：公司流动比率为3.2619，速动比率为1.9578，均处于较高水平。期末流动资产合计233.61亿元，远覆盖71.62亿元的流动负债 [数据来源: 已验证的合并报表原始数据]。公司通过保持充分的现金及现金等价物来满足经营需要，有效降低了流动性风险 [第200页]。\n2. **长期偿债能力**：公司资产负债率为0.3268（即32.68%），期末资产总计300.89亿元，负债合计98.32亿元 [数据来源: 已验证的合并报表原始数据]。该比率处于较低水平，表明公司长期偿债压力小，符合其“维持最佳的资本结构以降低资本成本”的资本管理目标 [第201页]。\n3. **破产风险评估（Z-Score）**：公司2023年度 Z''-Score 得分为 7.3957。根据判定标准（>2.60 为安全区），该数值远超临界值，明确处于“安全区” [数据来源: 财务指标计算结果]。其核心支撑因素包括充裕的营运资本（X1_营运资本/总资产为0.5384）、丰厚的留存收益（X2_留存收益/总资产为0.3182）以及极高的权益负债覆盖率（X4_账面权益/总负债为2.0603）。\n\n**四、营运能力分析**\n1. **应收账款周转情况**：应收账款周转率为15.1575，期末应收账款余额为10.56亿元 [数据来源: 已验证的合并报表原始数据]。该周转率处于较高水平，表明公司对下游客户具有较强的议价能力，货款回收速度快，资金占用少。\n2. **存货周转情况**：存货周转率为1.1742，期末存货绝对金额高达93.40亿元 [数据来源: 已验证的合并报表原始数据]。该周转率处于较低水平，反映了中药行业原材料储备及生产周期的特殊性。公司管理层需持续通过周转率、库龄等分析指标评价存货滞销迹象 [第71页]。\n3. **总资产周转情况**：总资产周转率为0.6251，在庞大的存货基数下，公司依然维持了正常的整体资产运营效率。\n\n**五、综合评价与风险提示**\n**综合评价**：\n同仁堂在2023年度展现出了优秀的财务健康度。公司盈利能力扎实（ROE稳步提升），资本结构极为稳健（低资产负债率、高流动比率），且 Z''-Score 破产模型显示公司处于绝对的安全区，整体财务风险极低。\n\n**风险提示与关注事项**：\n1. **成本控制压力**：报告期内营业成本增速（19.62%）快于营业收入增速（16.19%），导致医药工业板块毛利率出现1.98个百分点的下滑 [第15页 / 第16页]，建议投资者关注原材料价格波动对公司盈利空间的挤压效应。\n2. **存货规模与减值风险**：期末存货高达93.40亿元，占总资产（300.89亿元）比重超30%，且存货周转率（1.1742）处于较低水平。尽管这符合行业特性，但仍需密切关注长库龄存货可能带来的滞销与跌价减值风险 [第71页]。",
  "consistency_report": {
    "rule_checks": [
      {
        "type": "value_citation_mismatch",
        "severity": "low",
        "detail": "解读中引用了 16.19%，未找到匹配的计算指标值"
      },
      {
        "type": "value_citation_mismatch",
        "severity": "low",
        "detail": "解读中引用了 19.62%，未找到匹配的计算指标值"
      },
      {
        "type": "value_citation_mismatch",
        "severity": "low",
        "detail": "解读中引用了 19.62%，未找到匹配的计算指标值"
      },
      {
        "type": "value_citation_mismatch",
        "severity": "low",
        "detail": "解读中引用了 16.19%，未找到匹配的计算指标值"
      },
      {
        "type": "value_citation_mismatch",
        "severity": "low",
        "detail": "解读中引用了 19.62%，未找到匹配的计算指标值"
      },
      {
        "type": "value_citation_mismatch",
        "severity": "low",
        "detail": "解读中引用了 16.19%，未找到匹配的计算指标值"
      }
    ],
    "semantic_checks": [],
    "summary": {
      "total_issues": 6,
      "high": 0,
      "medium": 0,
      "low": 6,
      "passed": true
    }
  },
  "errors": [],
  "extracted_values": {
    "营业收入": 17860891456.13,
    "营业成本": 9414070490.87,
    "净利润": 2583225229.82,
    "利润总额": 3080653857.39,
    "财务费用": -110139252.35,
    "所得税费用": 497428627.57,
    "资产总计": 30089450163.66,
    "流动资产合计": 23361225804.93,
    "流动负债合计": 7161813676.68,
    "负债合计": 9832343990.7,
    "所有者权益合计": 20257106172.96,
    "存货": 9340164542.46,
    "应收账款": 1055560325.33,
    "未分配利润": 8370702732.85,
    "盈余公积": 1203627139.51,
    "期初资产总计": 27054123244.38,
    "期初所有者权益合计": 18463699667.910004,
    "期初应收账款": 1301148434.72,
    "期初存货": 6694368428.37
  },
  "timestamp": "2026-03-28T20:14:22.663206"
}