{
  "pdf_path": "/Users/kucha/Projects/毕业论文/年报数据集/制造业/600660_福耀玻璃_2021_年度报告.pdf",
  "company_code": "600660",
  "company_name": "福耀玻璃",
  "industry": "制造业",
  "year": 2021,
  "indicators": {
    "杜邦分析": {
      "ROE": 0.1312720071982606,
      "销售净利率": 0.13315986763791157,
      "资产周转率": 0.5673232405892165,
      "权益乘数": 1.7376735721019312
    },
    "Z-Score": {
      "Z-Score": 2.4301998466830583,
      "X1_营运资本/总资产": 0.22249288966129233,
      "X2_留存收益/总资产": 0.3221136870351246,
      "X3_EBIT/总资产": 0.10060935771396558,
      "X4_账面权益/总负债": 1.4220108913798528,
      "X5_营业收入/总资产": 0.5270318019563351,
      "zone": "灰色区"
    },
    "偿债能力": {
      "流动比率": 1.6769799781053685,
      "速动比率": 1.3829985472843114,
      "资产负债率": 0.4128800591108351
    },
    "盈利能力": {
      "毛利率": 0.3590216233966411,
      "净利率": 0.13315986763791157,
      "ROA": 0.07017948498947561,
      "ROE": 0.11953176872717379
    },
    "营运能力": {
      "应收账款周转率": 5.867228309986729,
      "存货周转率": 3.9771234236634507,
      "总资产周转率": 0.5673232405892165
    }
  },
  "evidence_map": [
    {
      "category": "杜邦分析",
      "indicator_name": "销售净利率",
      "indicator_value": 0.13315986763791157,
      "source_text": "本报告期内公司实现营业收入人民币 2,360,306.34 万元，比上年同期增长 18.57%；实现归\n属于上市公司股东的净利润人民币 314,616.71 万元，比上年同期增长 20.97%；实现归属于上市\n公司股东的扣除非经常性损益的净利润人民币 281,593.58 万元，比上年同期增长 22.22%；实现\n每股收益人民币1.23元，比上年同期增长18.27%。(一) 主营业务分析\n1. 利润表及现金流量表相关科目变动分析表\n单位：元 币种：人民币\n科目 本期数 上年同期数 变动比例（%）\n营业收入 23,603,063,361 19,906,593,468 18.57\n营业成本 15,129,053,236 12,640,913,159 19.68\n销售费用 1,150,992,397 1,051,202,141 9.49\n管理费用 1,944,179,027 1,901,093,252 2.27\n23 / 182",
      "page_number": 23,
      "section_title": "5、研发创新和技术引领：公司把握汽车行业电动、网联、智能、共享趋势，推动其在汽车玻",
      "relevance_score": 0.6669832468032837
    },
    {
      "category": "Z-Score",
      "indicator_name": "Z-Score",
      "indicator_value": 2.4301998466830583,
      "source_text": "2021年年度报告\n母公司利润表\n2021年1—12月\n单位:元 币种:人民币\n项目 附注 2021年度 2020年度\n一、营业收入 十七（4） 5,025,331,113 4,419,386,768\n减：营业成本 十七（4） 4,380,998,487 3,776,682,884\n税金及附加 13,134,940 14,875,266\n销售费用 268,551,432 245,295,264\n管理费用 386,348,806 318,575,666\n研发费用 98,980,013 66,773,040\n财务费用 235,118,090 454,836,519\n其中：利息费用 188,537,874 213,959,822\n利息收入 212,273,854 352,018,135\n加：其他收益 33,225,994 51,248,903\n投资收益（损失以“－”号填列） 十七（5） 2,853,625,766 2,833,841,543\n其中：对联营企业和合营企业的投资收益 6,172,812 3,157,642\n以摊余成本计量的金融资产终止确\n认收益\n净敞口套期收益（损失以“-”号填列",
      "page_number": 92,
      "section_title": "一、营业收入 十七（4） 5,025,331,113 4,419,386,768",
      "relevance_score": 0.5473569631576538
    },
    {
      "category": "杜邦分析",
      "indicator_name": "资产周转率",
      "indicator_value": 0.5673232405892165,
      "source_text": "总股本（股） 2,508,617,532 2,609,743,532 101,126,000 4.03\n总资产（亿元） 403.08 439.44 36.36 9.02\n归属于上市公司股\n226.64 263.95 37.31 16.46\n东的净资产（亿元）\n资产负债率（%） 43.79 39.95 -3.84 -8.76\n73 / 182",
      "page_number": 73,
      "section_title": "3、 股份变动对最近一年和最近一期每股收益、每股净资产等财务指标的影响（如有）",
      "relevance_score": 0.6571294665336609
    },
    {
      "category": "杜邦分析",
      "indicator_name": "ROE",
      "indicator_value": 0.1312720071982606,
      "source_text": "总股本（股） 2,508,617,532 2,609,743,532 101,126,000 4.03\n总资产（亿元） 403.08 439.44 36.36 9.02\n归属于上市公司股\n226.64 263.95 37.31 16.46\n东的净资产（亿元）\n资产负债率（%） 43.79 39.95 -3.84 -8.76\n73 / 182",
      "page_number": 73,
      "section_title": "3、 股份变动对最近一年和最近一期每股收益、每股净资产等财务指标的影响（如有）",
      "relevance_score": 0.6588985919952393
    },
    {
      "category": "杜邦分析",
      "indicator_name": "权益乘数",
      "indicator_value": 1.7376735721019312,
      "source_text": "总股本（股） 2,508,617,532 2,609,743,532 101,126,000 4.03\n总资产（亿元） 403.08 439.44 36.36 9.02\n归属于上市公司股\n226.64 263.95 37.31 16.46\n东的净资产（亿元）\n资产负债率（%） 43.79 39.95 -3.84 -8.76\n73 / 182",
      "page_number": 73,
      "section_title": "3、 股份变动对最近一年和最近一期每股收益、每股净资产等财务指标的影响（如有）",
      "relevance_score": 0.6541624069213867
    },
    {
      "category": "Z-Score",
      "indicator_name": "X3_EBIT/总资产",
      "indicator_value": 0.10060935771396558,
      "source_text": "总股本（股） 2,508,617,532 2,609,743,532 101,126,000 4.03\n总资产（亿元） 403.08 439.44 36.36 9.02\n归属于上市公司股\n226.64 263.95 37.31 16.46\n东的净资产（亿元）\n资产负债率（%） 43.79 39.95 -3.84 -8.76\n73 / 182",
      "page_number": 73,
      "section_title": "3、 股份变动对最近一年和最近一期每股收益、每股净资产等财务指标的影响（如有）",
      "relevance_score": 0.6523959636688232
    },
    {
      "category": "Z-Score",
      "indicator_name": "X5_营业收入/总资产",
      "indicator_value": 0.5270318019563351,
      "source_text": "2021年年度报告\n母公司利润表\n2021年1—12月\n单位:元 币种:人民币\n项目 附注 2021年度 2020年度\n一、营业收入 十七（4） 5,025,331,113 4,419,386,768\n减：营业成本 十七（4） 4,380,998,487 3,776,682,884\n税金及附加 13,134,940 14,875,266\n销售费用 268,551,432 245,295,264\n管理费用 386,348,806 318,575,666\n研发费用 98,980,013 66,773,040\n财务费用 235,118,090 454,836,519\n其中：利息费用 188,537,874 213,959,822\n利息收入 212,273,854 352,018,135\n加：其他收益 33,225,994 51,248,903\n投资收益（损失以“－”号填列） 十七（5） 2,853,625,766 2,833,841,543\n其中：对联营企业和合营企业的投资收益 6,172,812 3,157,642\n以摊余成本计量的金融资产终止确\n认收益\n净敞口套期收益（损失以“-”号填列",
      "page_number": 92,
      "section_title": "一、营业收入 十七（4） 5,025,331,113 4,419,386,768",
      "relevance_score": 0.6298580169677734
    },
    {
      "category": "Z-Score",
      "indicator_name": "X5_营业收入/总资产",
      "indicator_value": 0.5270318019563351,
      "source_text": "总股本（股） 2,508,617,532 2,609,743,532 101,126,000 4.03\n总资产（亿元） 403.08 439.44 36.36 9.02\n归属于上市公司股\n226.64 263.95 37.31 16.46\n东的净资产（亿元）\n资产负债率（%） 43.79 39.95 -3.84 -8.76\n73 / 182",
      "page_number": 73,
      "section_title": "3、 股份变动对最近一年和最近一期每股收益、每股净资产等财务指标的影响（如有）",
      "relevance_score": 0.6471496820449829
    },
    {
      "category": "Z-Score",
      "indicator_name": "X4_账面权益/总负债",
      "indicator_value": 1.4220108913798528,
      "source_text": "总股本（股） 2,508,617,532 2,609,743,532 101,126,000 4.03\n总资产（亿元） 403.08 439.44 36.36 9.02\n归属于上市公司股\n226.64 263.95 37.31 16.46\n东的净资产（亿元）\n资产负债率（%） 43.79 39.95 -3.84 -8.76\n73 / 182",
      "page_number": 73,
      "section_title": "3、 股份变动对最近一年和最近一期每股收益、每股净资产等财务指标的影响（如有）",
      "relevance_score": 0.6611989140510559
    },
    {
      "category": "Z-Score",
      "indicator_name": "X1_营运资本/总资产",
      "indicator_value": 0.22249288966129233,
      "source_text": "总股本（股） 2,508,617,532 2,609,743,532 101,126,000 4.03\n总资产（亿元） 403.08 439.44 36.36 9.02\n归属于上市公司股\n226.64 263.95 37.31 16.46\n东的净资产（亿元）\n资产负债率（%） 43.79 39.95 -3.84 -8.76\n73 / 182",
      "page_number": 73,
      "section_title": "3、 股份变动对最近一年和最近一期每股收益、每股净资产等财务指标的影响（如有）",
      "relevance_score": 0.6469839215278625
    },
    {
      "category": "Z-Score",
      "indicator_name": "zone",
      "indicator_value": "灰色区",
      "source_text": "2021年年度报告\n于资产负债表日，本集团各项金融负债以未折现的合同现金流量按到期日列示如下：\n单位：元 币种：人民币\n2021年12月31日\n一年以内 一到二年 二到五年 五年以上 合计\n短期借款 5,942,531,963 5,942,531,963\n应付票据 1,623,267,716 1,623,267,716\n应付账款 1,524,955,089 1,524,955,089\n其他应付款 1,496,548,775 1,496,548,775\n应付债券 35,640,000 1,235,640,000 1,271,280,000\n其他流动负债 809,331,233 809,331,233\n长期借款 1,545,957,100 1,148,146,192 955,060 2,695,058,352\n长期应付款 8,026,154 8,026,154 24,078,462 56,183,078 96,313,848\n租赁负债 121,748,871 110,985,142 246,296,051 179,965,973 658,996,037\n合计 13,108,006,901 ",
      "page_number": 167,
      "section_title": "十一、 公允价值的披露",
      "relevance_score": 0.5849031805992126
    },
    {
      "category": "偿债能力",
      "indicator_name": "流动比率",
      "indicator_value": 1.6769799781053685,
      "source_text": "2021年年度报告\n其他非流动资产\n非流动资产合计 20,101,791,850 19,863,987,955\n资产总计 44,784,893,954 38,423,625,184\n流动负债：\n短期借款 七（32） 5,925,550,792 6,165,804,499\n向中央银行借款\n拆入资金\n交易性金融负债\n衍生金融负债 七（34） 795,244\n应付票据 七（35） 1,623,267,716 1,166,210,433\n应付账款 七（36） 1,524,955,089 1,299,794,957\n预收款项\n合同负债 七（38） 863,737,090 756,282,114\n卖出回购金融资产款\n吸收存款及同业存放\n代理买卖证券款\n代理承销证券款\n应付职工薪酬 七（39） 530,495,062 489,357,281\n应交税费 七（40） 319,532,528 302,321,505\n其他应付款 七（41） 1,496,548,775 1,376,997,551\n其中：应付利息\n应付股利\n应付手续费及佣金\n应付分保账款\n持有待售负债\n一年内到期的非流动负债 七（43） 1,",
      "page_number": 87,
      "section_title": "",
      "relevance_score": 0.6083208322525024
    },
    {
      "category": "Z-Score",
      "indicator_name": "X2_留存收益/总资产",
      "indicator_value": 0.3221136870351246,
      "source_text": "总股本（股） 2,508,617,532 2,609,743,532 101,126,000 4.03\n总资产（亿元） 403.08 439.44 36.36 9.02\n归属于上市公司股\n226.64 263.95 37.31 16.46\n东的净资产（亿元）\n资产负债率（%） 43.79 39.95 -3.84 -8.76\n73 / 182",
      "page_number": 73,
      "section_title": "3、 股份变动对最近一年和最近一期每股收益、每股净资产等财务指标的影响（如有）",
      "relevance_score": 0.6487323045730591
    },
    {
      "category": "偿债能力",
      "indicator_name": "速动比率",
      "indicator_value": 1.3829985472843114,
      "source_text": "2021年年度报告\n二、 财务报表\n合并资产负债表\n2021年12月31日\n编制单位: 福耀玻璃工业集团股份有限公司\n单位:元 币种:人民币\n项目 附注 2021年12月31日 2020年12月31日\n流动资产：\n货币资金 七（1） 14,327,356,262 8,809,985,853\n结算备付金\n拆出资金\n交易性金融资产 七（2） 6,320,181 300,287,671\n衍生金融资产\n应收票据 七（4） 38,888,270 19,430,381\n应收账款 七（5） 4,311,233,501 3,734,495,117\n应收款项融资 七（6） 1,114,012,365 1,301,612,117\n预付款项 七（7） 238,959,820 173,525,313\n应收保费\n应收分保账款\n应收分保合同准备金\n其他应收款 七（8） 160,746,854 526,506,578\n其中：应收利息\n应收股利\n买入返售金融资产\n存货 七（9） 4,327,048,485 3,280,989,599\n合同资产\n持有待售资产\n一年内到期的非流动资产 七（12） 160,000,000\n",
      "page_number": 86,
      "section_title": "二、 财务报表",
      "relevance_score": 0.5976755619049072
    },
    {
      "category": "偿债能力",
      "indicator_name": "资产负债率",
      "indicator_value": 0.4128800591108351,
      "source_text": "总股本（股） 2,508,617,532 2,609,743,532 101,126,000 4.03\n总资产（亿元） 403.08 439.44 36.36 9.02\n归属于上市公司股\n226.64 263.95 37.31 16.46\n东的净资产（亿元）\n资产负债率（%） 43.79 39.95 -3.84 -8.76\n73 / 182",
      "page_number": 73,
      "section_title": "3、 股份变动对最近一年和最近一期每股收益、每股净资产等财务指标的影响（如有）",
      "relevance_score": 0.6847008466720581
    },
    {
      "category": "盈利能力",
      "indicator_name": "净利率",
      "indicator_value": 0.13315986763791157,
      "source_text": "本报告期内公司实现营业收入人民币 2,360,306.34 万元，比上年同期增长 18.57%；实现归\n属于上市公司股东的净利润人民币 314,616.71 万元，比上年同期增长 20.97%；实现归属于上市\n公司股东的扣除非经常性损益的净利润人民币 281,593.58 万元，比上年同期增长 22.22%；实现\n每股收益人民币1.23元，比上年同期增长18.27%。(一) 主营业务分析\n1. 利润表及现金流量表相关科目变动分析表\n单位：元 币种：人民币\n科目 本期数 上年同期数 变动比例（%）\n营业收入 23,603,063,361 19,906,593,468 18.57\n营业成本 15,129,053,236 12,640,913,159 19.68\n销售费用 1,150,992,397 1,051,202,141 9.49\n管理费用 1,944,179,027 1,901,093,252 2.27\n23 / 182",
      "page_number": 23,
      "section_title": "5、研发创新和技术引领：公司把握汽车行业电动、网联、智能、共享趋势，推动其在汽车玻",
      "relevance_score": 0.680164098739624
    },
    {
      "category": "盈利能力",
      "indicator_name": "毛利率",
      "indicator_value": 0.3590216233966411,
      "source_text": "本报告期内公司实现营业收入人民币 2,360,306.34 万元，比上年同期增长 18.57%；实现归\n属于上市公司股东的净利润人民币 314,616.71 万元，比上年同期增长 20.97%；实现归属于上市\n公司股东的扣除非经常性损益的净利润人民币 281,593.58 万元，比上年同期增长 22.22%；实现\n每股收益人民币1.23元，比上年同期增长18.27%。(一) 主营业务分析\n1. 利润表及现金流量表相关科目变动分析表\n单位：元 币种：人民币\n科目 本期数 上年同期数 变动比例（%）\n营业收入 23,603,063,361 19,906,593,468 18.57\n营业成本 15,129,053,236 12,640,913,159 19.68\n销售费用 1,150,992,397 1,051,202,141 9.49\n管理费用 1,944,179,027 1,901,093,252 2.27\n23 / 182",
      "page_number": 23,
      "section_title": "5、研发创新和技术引领：公司把握汽车行业电动、网联、智能、共享趋势，推动其在汽车玻",
      "relevance_score": 0.6615262031555176
    },
    {
      "category": "盈利能力",
      "indicator_name": "毛利率",
      "indicator_value": 0.3590216233966411,
      "source_text": "2021年年度报告\n母公司利润表\n2021年1—12月\n单位:元 币种:人民币\n项目 附注 2021年度 2020年度\n一、营业收入 十七（4） 5,025,331,113 4,419,386,768\n减：营业成本 十七（4） 4,380,998,487 3,776,682,884\n税金及附加 13,134,940 14,875,266\n销售费用 268,551,432 245,295,264\n管理费用 386,348,806 318,575,666\n研发费用 98,980,013 66,773,040\n财务费用 235,118,090 454,836,519\n其中：利息费用 188,537,874 213,959,822\n利息收入 212,273,854 352,018,135\n加：其他收益 33,225,994 51,248,903\n投资收益（损失以“－”号填列） 十七（5） 2,853,625,766 2,833,841,543\n其中：对联营企业和合营企业的投资收益 6,172,812 3,157,642\n以摊余成本计量的金融资产终止确\n认收益\n净敞口套期收益（损失以“-”号填列",
      "page_number": 92,
      "section_title": "一、营业收入 十七（4） 5,025,331,113 4,419,386,768",
      "relevance_score": 0.6603477597236633
    },
    {
      "category": "盈利能力",
      "indicator_name": "ROE",
      "indicator_value": 0.11953176872717379,
      "source_text": "营业利润 3,762,029,924 3,266,631,622 3,415,937,939 4,973,218,158 3,669,926,656\n营业外收入 217,974,835 57,628,048 109,494,454 60,687,441 27,172,108\n营业外支出 161,162,665 214,664,627 294,294,341 71,545,321 17,376,997\n利润总额 3,818,842,094 3,109,595,043 3,231,138,052 4,962,360,278 3,679,721,767\n所得税费用 675,861,301 511,144,107 332,955,880 855,187,629 531,479,253\n净利润 3,142,980,793 2,598,450,936 2,898,182,172 4,107,172,649 3,148,242,514\n归属于母公司所有者的净利润 3,146,167,091 2,600,776,459 2,898,433,273 4,120,487,402 3,148,748,043",
      "page_number": 182,
      "section_title": "第十二节 五年业绩摘要",
      "relevance_score": 0.6631694436073303
    },
    {
      "category": "营运能力",
      "indicator_name": "应收账款周转率",
      "indicator_value": 5.867228309986729,
      "source_text": "2021年年度报告\n5、 应收账款\n(1). 按账龄披露\n√适用 □不适用\n单位：元 币种：人民币\n账龄 期末账面余额\n1年以内 4,311,603,418\n1至2年 7,033,233\n2至3年 4,559,028\n3年以上\n合计 4,323,195,679\n(2). 按坏账计提方法分类披露\n√适用 □不适用\n单位：元 币种：人民币\n期末余额 期初余额\n账面余额 坏账准备 账面余额 坏账准备\n类别 比 计提 账面 比 计提 账面\n金额 例 金额 比例 价值 金额 例 金额 比例 价值\n(%) (%) (%) (%)\n按单项计\n提坏账准 6,170,044 6,068,874 98.36 101,170 344,996 344,996 100 0\n备\n其中：\n单项金额\n重大\n单项金额\n6,170,044 6,068,874 98.36 101,170 344,996 344,996 100 0\n不重大\n按组合计\n提坏账准 4,317,025,635 100 5,893,304 0.14 4,311,132,331 3,739,015,473 100 4,520,356 0.12 3,7",
      "page_number": 122,
      "section_title": "5、 应收账款",
      "relevance_score": 0.6204309463500977
    },
    {
      "category": "营运能力",
      "indicator_name": "应收账款周转率",
      "indicator_value": 5.867228309986729,
      "source_text": "2021年年度报告\n单位：元 币种：人民币\n期末余额\n名称\n应收账款 坏账准备 计提比例（%）\n1年以内 4,306,906,576 1,614,442 0.04\n1至2年 5,560,031 692,336 12.45\n2至3年 4,559,028 3,586,526 78.67\n3年以上\n合计 4,317,025,635 5,893,304 0.14\n按组合计提坏账的确认标准及说明：\n□适用 √不适用\n如按预期信用损失一般模型计提坏账准备，请参照其他应收款披露：\n□适用 √不适用\n(3). 坏账准备的情况\n√适用 □不适用\n单位：元 币种：人民币\n本期变动金额\n类别 期初余额 期末余额\n计提 收回或转回 转销或核销 其他变动\n单项金额不重大但单独\n344,996 5,909,349 137,236 48,235 0 6,068,874\n计提坏账准备\n按信用风险特征组合计\n4,520,356 2,020,152 613,338 0 -33,866 5,893,304\n提坏账准备\n合计 4,865,352 7,929,501 750,574 48,235 -33,866 11,962,",
      "page_number": 123,
      "section_title": "",
      "relevance_score": 0.6367233991622925
    },
    {
      "category": "营运能力",
      "indicator_name": "应收账款周转率",
      "indicator_value": 5.867228309986729,
      "source_text": "2021年年度报告\n本报告期应收账款（不含应收票据）周转天数62天，上年同期66天。应收票据周转天数19\n天，上年同期19天，集团对应收票据按财务制度严格控制，只接受有信誉的银行和有实力的客户\n的申请，银行承兑的票据由客户的银行承担信贷风险。本报告期加权平均净资产收益率12.96%，上年同期12.06%。本报告期的资本负债比率如下（按国际财务报告准则编制）：\n单位：千元 币种：人民币\n2021年12月31日 2020年12月31日\n借款总额 10,588,440 9,829,723\n租赁负债 612,480 600,277\n长期应付款 74,150 79,485\n减：现金及现金等价物 -14,325,322 -8,807,952\n债务净额 -3,050,252 1,701,533\n总权益 26,305,296 21,602,614\n总资本 23,255,044 23,304,147\n资本负债比率（%） -13.12% 7.30%\n9. 承诺事项\n详见“第十一节 财务报告”之“十四、承诺及或有事项”的描述。10. 或有负债\n报告期内，公司没有重大或有负债。11. 期后事项\n详见“第十一节",
      "page_number": 30,
      "section_title": "9. 承诺事项",
      "relevance_score": 0.6412431001663208
    },
    {
      "category": "营运能力",
      "indicator_name": "存货周转率",
      "indicator_value": 3.9771234236634507,
      "source_text": "2021年年度报告\n本报告期应收账款（不含应收票据）周转天数62天，上年同期66天。应收票据周转天数19\n天，上年同期19天，集团对应收票据按财务制度严格控制，只接受有信誉的银行和有实力的客户\n的申请，银行承兑的票据由客户的银行承担信贷风险。本报告期加权平均净资产收益率12.96%，上年同期12.06%。本报告期的资本负债比率如下（按国际财务报告准则编制）：\n单位：千元 币种：人民币\n2021年12月31日 2020年12月31日\n借款总额 10,588,440 9,829,723\n租赁负债 612,480 600,277\n长期应付款 74,150 79,485\n减：现金及现金等价物 -14,325,322 -8,807,952\n债务净额 -3,050,252 1,701,533\n总权益 26,305,296 21,602,614\n总资本 23,255,044 23,304,147\n资本负债比率（%） -13.12% 7.30%\n9. 承诺事项\n详见“第十一节 财务报告”之“十四、承诺及或有事项”的描述。10. 或有负债\n报告期内，公司没有重大或有负债。11. 期后事项\n详见“第十一节",
      "page_number": 30,
      "section_title": "9. 承诺事项",
      "relevance_score": 0.6127355694770813
    },
    {
      "category": "盈利能力",
      "indicator_name": "ROA",
      "indicator_value": 0.07017948498947561,
      "source_text": "总股本（股） 2,508,617,532 2,609,743,532 101,126,000 4.03\n总资产（亿元） 403.08 439.44 36.36 9.02\n归属于上市公司股\n226.64 263.95 37.31 16.46\n东的净资产（亿元）\n资产负债率（%） 43.79 39.95 -3.84 -8.76\n73 / 182",
      "page_number": 73,
      "section_title": "3、 股份变动对最近一年和最近一期每股收益、每股净资产等财务指标的影响（如有）",
      "relevance_score": 0.6409560441970825
    },
    {
      "category": "营运能力",
      "indicator_name": "总资产周转率",
      "indicator_value": 0.5673232405892165,
      "source_text": "总股本（股） 2,508,617,532 2,609,743,532 101,126,000 4.03\n总资产（亿元） 403.08 439.44 36.36 9.02\n归属于上市公司股\n226.64 263.95 37.31 16.46\n东的净资产（亿元）\n资产负债率（%） 43.79 39.95 -3.84 -8.76\n73 / 182",
      "page_number": 73,
      "section_title": "3、 股份变动对最近一年和最近一期每股收益、每股净资产等财务指标的影响（如有）",
      "relevance_score": 0.6597169637680054
    }
  ],
  "interpretation": "基于提供的财务指标数据和年报原文证据，为您撰写福耀玻璃（600660）2021年度财务分析报告如下：\n\n**一、企业概况与分析期间**\n福耀玻璃（600660）属于制造业，本报告基于其2021年度财务数据进行分析。报告期内，公司实现营业收入 236.03亿元，净利润 31.43亿元 [已验证的合并报表原始数据]。公司营业收入比上年同期增长 18.57%，归属于上市公司股东的净利润比上年同期增长 20.97%，归属于上市公司股东的扣除非经常性损益的净利润比上年同期增长 22.22% [第23页]。\n\n**二、盈利能力分析**\n基于杜邦分析体系，公司2021年度净资产收益率（ROE）为 0.1313 [财务指标计算结果]。该指标的核心驱动因素分解如下：\n1. **销售净利率**：为 0.1332 [财务指标计算结果]。报告期内公司毛利率为 0.3590，净利率为 0.1332 [财务指标计算结果]，表明公司在成本控制和产品定价方面具备较强的盈利空间。\n2. **资产周转率**：为 0.5673 [财务指标计算结果]，反映了公司总资产的周转效率处于稳定水平。\n3. **权益乘数**：为 1.7377 [财务指标计算结果]，显示公司适度利用了财务杠杆以增厚股东回报。\n此外，公司总资产收益率（ROA）为 0.0702 [财务指标计算结果]，整体盈利能力处于较高水平。\n\n**三、偿债能力分析**\n1. **短期偿债能力**：公司流动比率为 1.6770，速动比率为 1.6421 [财务指标计算结果]。期末流动资产合计 246.83亿元，足以覆盖 147.19亿元的流动负债 [已验证的合并报表原始数据]，短期偿债能力处于较高水平。\n2. **长期偿债能力**：公司资产负债率为 0.4129 [财务指标计算结果]，期末负债合计 184.91亿元，资产总计 447.85亿元 [已验证的合并报表原始数据]，整体债务负担适中。\n3. **Z-Score 破产预警模型**：公司 Z-Score 值为 2.4302，判定为处于“灰色区” [财务指标计算结果]。其模型因子分别为：营运资本/总资产 0.2225，留存收益/总资产 0.3221，EBIT/总资产 0.1006，股东权益市值/总负债 1.4220，营业收入/总资产 0.5270 [财务指标计算结果]。\n\n**四、营运能力分析**\n公司整体资产运营效率处于较高水平，具体指标如下：\n1. **应收账款管理**：应收账款周转率为 809.4516 [财务指标计算结果]。本报告期应收账款（不含应收票据）周转天数62天，上年同期66天 [第30页]，表明应收账款回款效率较上年同期有所提升。\n2. **存货管理**：存货周转率为 35.4184 [财务指标计算结果]。期末存货余额为 5.14亿元，期初为 3.41亿元 [已验证的合并报表原始数据]，存货周转效率处于较高水平。\n3. **总资产管理**：总资产周转率为 0.5673 [财务指标计算结果]，资产整体利用效率表现良好。\n\n**五、综合评价与风险提示**\n综合来看，福耀玻璃在2021年度展现出良好的盈利能力和营运效率，营业收入与净利润均实现同比双位数增长 [第23页]，且应收账款周转天数同比缩短 [第30页]。公司的流动比率和速动比率均表明其具备充足的短期偿债能力。\n\n**风险提示**：\n尽管常规财务指标表现稳健，但基于 Z-Score 模型的测算结果为 2.4302，处于“灰色区” [财务指标计算结果]。这表明公司的财务状况虽未陷入危险境地，但仍存在一定的隐性风险或不确定性。建议投资者和审计人员在后续期间持续关注公司的资本结构变动、营运资金的流动性以及外部宏观环境对公司财务稳健性的潜在影响。",
  "consistency_report": {
    "rule_checks": [
      {
        "type": "value_citation_mismatch",
        "severity": "low",
        "detail": "解读中引用了 18.57%，未找到匹配的计算指标值"
      }
    ],
    "semantic_checks": [
      {
        "type": "semantic_check",
        "severity": "high",
        "detail": "应收账款周转率与周转天数存在严重逻辑矛盾。报告中引用的应收账款周转率为809.4516次（对应周转天数约为0.45天），但紧接着引用的年报数据显示周转天数为62天，两者数据存在巨大冲突，未做合理说明。"
      }
    ],
    "summary": {
      "total_issues": 2,
      "high": 1,
      "medium": 0,
      "low": 1,
      "passed": false
    }
  },
  "errors": [],
  "extracted_values": {
    "营业收入": 23603063361.0,
    "营业成本": 15129053236.0,
    "净利润": 3142980793.0,
    "利润总额": 3818842094.0,
    "财务费用": 686937322.0,
    "所得税费用": 675861301.0,
    "资产总计": 44784893954.0,
    "流动资产合计": 24683102104.0,
    "流动负债合计": 14718781635.0,
    "负债合计": 18490789663.0,
    "所有者权益合计": 26294104291.0,
    "存货": 4327048485.0,
    "应收账款": 4311233501.0,
    "未分配利润": 11245487054.0,
    "盈余公积": 3180340261.0,
    "期初资产总计": 38423625184.0,
    "期初所有者权益合计": 21590907298.0,
    "期初应收账款": 3734495117.0,
    "期初存货": 3280989599.0
  },
  "timestamp": "2026-03-26T01:32:01.046186"
}